{
  "date_published": 1662595200,
  "name": "Concrete Wall 004",
  "type": 1,
  "reviewers": [
    "Rico Cilliers"
  ],
  "staging": null,
  "authors": {
    "Dario Barresi": "Processing",
    "Charlotte Baglioni": "Photography"
  },
  "info": null,
  "dimensions": [
    2000,
    2000
  ],
  "categories": [
    "man made",
    "wall",
    "plaster-concrete",
    "concrete",
    "collection: the_shed"
  ],
  "tags": [
    "worn",
    "painted",
    "dry",
    "flat",
    "wall",
    "stained",
    "dirty",
    "weathered"
  ],
  "max_resolution": [
    8192,
    8192
  ],
  "files_hash": "259e8b2759d2524af008c5df1505eddd7df3b0ba",
  "download_count": 46896,
  "thumbnail_url": "https://cdn.polyhaven.com/asset_img/thumbs/concrete_wall_004.png?width=256&height=256"
}