{
  "evs_cap": 22,
  "type": 0,
  "reviewers": [
    "Greg Zaal"
  ],
  "whitebalance": 5303,
  "tags": [
    "mountain",
    "view",
    "dam",
    "lake",
    "hilltop",
    "grass",
    "sun"
  ],
  "name": "Qwantani Sunset",
  "categories": [
    "outdoor",
    "natural light",
    "nature",
    "skies",
    "medium contrast",
    "sunrise-sunset",
    "partly cloudy"
  ],
  "date_taken": 1724000940,
  "coords": [
    -28.48533209827116,
    29.012639559934758
  ],
  "authors": {
    "Greg Zaal": "Photography",
    "Jarod Guest": "Processing"
  },
  "max_resolution": [
    24576,
    12288
  ],
  "files_hash": "96a6255c2f908c8dab0770f29f3e5fd16e787f03",
  "date_published": 1730851200,
  "staging": null,
  "download_count": 41819,
  "thumbnail_url": "https://cdn.polyhaven.com/asset_img/thumbs/qwantani_sunset.png?width=256&height=256"
}