{
  "date_published": 1530836328,
  "name": "Brown Mud Dry",
  "old_id": 146,
  "type": 1,
  "authors": {
    "Rob Tuytel": "All"
  },
  "dimensions": [
    1299.996018409729,
    1299.996018409729
  ],
  "categories": [
    "terrain",
    "natural",
    "outdoor",
    "collection: the_shed"
  ],
  "tags": [
    "mud",
    "dirt",
    "stones",
    "dry",
    "ground"
  ],
  "max_resolution": [
    8192,
    8192
  ],
  "files_hash": "bc73d5f8aa2cd4217f2f3e911cd9ab6fdbb1a221",
  "download_count": 116670,
  "thumbnail_url": "https://cdn.polyhaven.com/asset_img/thumbs/brown_mud_dry.png?width=256&height=256"
}