{
  "name": "Clay Roof Tiles",
  "categories": [
    "roofing"
  ],
  "type": 1,
  "reviewers": [
    "Dario Barresi",
    "Rob Tuytel"
  ],
  "tags": [
    "weathered",
    "rough",
    "worn",
    "uneven",
    "discolored",
    "clay",
    "roof",
    "roofing",
    "tile roofing",
    "exterior"
  ],
  "authors": {
    "Amal Kumar": "All"
  },
  "max_resolution": [
    8192,
    8192
  ],
  "dimensions": [
    4000,
    4000
  ],
  "date_published": 1718841600,
  "staging": null,
  "files_hash": "045b0a54a86afd93f6571c76296aa2df436a4328",
  "download_count": 9050,
  "thumbnail_url": "https://cdn.polyhaven.com/asset_img/thumbs/clay_roof_tiles.png?width=256&height=256"
}