{
  "lods": true,
  "name": "Namaqualand Boulder 05",
  "categories": [
    "collection: namaqualand",
    "nature",
    "rocks"
  ],
  "type": 2,
  "reviewers": [
    "James Ray Cock",
    "Rico Cilliers"
  ],
  "tags": [
    "karoo",
    "desert",
    "dry",
    "south africa"
  ],
  "authors": {
    "Jenelle van Heerden": "Model",
    "Dario Barresi": "Photography"
  },
  "max_resolution": [
    8192,
    8192
  ],
  "polycount": 117622,
  "texel_density": 4069.0480288941367,
  "dimensions": [
    1364.0307188034058,
    748.7391829490662,
    538.3217036724091
  ],
  "staging": null,
  "date_published": 1728345600,
  "files_hash": "db0437675da1e8fcd3fdd7b0d933cac1c9462456",
  "download_count": 6896,
  "thumbnail_url": "https://cdn.polyhaven.com/asset_img/thumbs/namaqualand_boulder_05.png?width=256&height=256"
}