{
  "type": 1,
  "tags": [
    "red",
    "rough",
    "old",
    "city",
    "factory",
    "industrial"
  ],
  "date_published": 1586487840,
  "name": "Church Bricks 02",
  "old_id": 250,
  "categories": [
    "brick",
    "man made",
    "outdoor"
  ],
  "authors": {
    "Rob Tuytel": "All"
  },
  "dimensions": [
    2000,
    2000
  ],
  "max_resolution": [
    8192,
    8192
  ],
  "files_hash": "35b5f13b0d69f4efea5845b6a80c60f5e2e17dab",
  "download_count": 46510,
  "thumbnail_url": "https://cdn.polyhaven.com/asset_img/thumbs/church_bricks_02.png?width=256&height=256"
}