{
  "type": 2,
  "tags": [
    "vintage",
    "photo",
    "photograph",
    "old",
    "antique",
    "picture",
    "fancy",
    "wooden",
    "varnished"
  ],
  "name": "Hanging Picture Frame 03",
  "categories": [
    "wall decoration",
    "decorative"
  ],
  "authors": {
    "James Ray Cock": "All"
  },
  "date_published": 1631664000,
  "staging": null,
  "max_resolution": [
    8192,
    8192
  ],
  "polycount": 24348,
  "texel_density": 13398.10794173108,
  "dimensions": [
    385.00405848026276,
    31.757352175191045,
    502.39527225494385
  ],
  "files_hash": "6861338cad64c7960760adaeb8df7d112daa8208",
  "download_count": 12737,
  "thumbnail_url": "https://cdn.polyhaven.com/asset_img/thumbs/hanging_picture_frame_03.png?width=256&height=256"
}