{
  "name": "Painted Concrete",
  "categories": [
    "floor",
    "indoor",
    "plaster-concrete",
    "concrete"
  ],
  "type": 1,
  "reviewers": [
    "Rico Cilliers",
    "Greg Zaal"
  ],
  "tags": [
    "weathered",
    "worn",
    "dirty",
    "damaged",
    "chipped",
    "cracked",
    "stained",
    "painted",
    "ground",
    "scratched",
    "flat",
    "floor",
    "concrete",
    "paint",
    "green"
  ],
  "info": null,
  "authors": {
    "Dario Barresi": "Processing",
    "Dimitrios Savva": "Photography"
  },
  "dimensions": [
    2000,
    2000
  ],
  "date_published": 1662422400,
  "staging": null,
  "max_resolution": [
    8192,
    8192
  ],
  "files_hash": "06bad4a77cd9cf78589919d9a7cc0d083f1065c0",
  "download_count": 63862,
  "thumbnail_url": "https://cdn.polyhaven.com/asset_img/thumbs/painted_concrete.png?width=256&height=256"
}