{
  "evs_cap": 9,
  "type": 0,
  "tags": [
    "street",
    "alley",
    "city",
    "asphalt",
    "building",
    "europe",
    "london",
    "road",
    "fence"
  ],
  "date_published": 1567116000,
  "name": "Urban Street 02",
  "old_id": 404,
  "categories": [
    "outdoor",
    "urban",
    "morning-afternoon",
    "overcast",
    "low contrast",
    "natural light"
  ],
  "date_taken": 1566110700,
  "coords": [
    51.526655,
    -0.056465
  ],
  "authors": {
    "Andreas Mischok": "All"
  },
  "max_resolution": [
    19310,
    9655
  ],
  "files_hash": "101dc4ed7256bcf9e04d58433d800d6f57f2fce1",
  "sponsors": [
    "42579608"
  ],
  "download_count": 56981,
  "thumbnail_url": "https://cdn.polyhaven.com/asset_img/thumbs/urban_street_02.png?width=256&height=256"
}