{
  "type": 2,
  "tags": [
    "barrel",
    "wine",
    "celler",
    "old",
    "worn",
    "grape",
    "farmhouse",
    "farm"
  ],
  "date_published": 1623767646,
  "sponsors": [
    "3267566"
  ],
  "name": "Wine Barrel 01",
  "categories": [
    "containers"
  ],
  "staging": null,
  "authors": {
    "James Ray Cock": "All"
  },
  "max_resolution": [
    8192,
    8192
  ],
  "polycount": 10820,
  "texel_density": 2580.2600580932635,
  "dimensions": [
    741.9015169143677,
    756.035715341568,
    871.2633550167084
  ],
  "files_hash": "943d486d1d003b1f56157522fd5382e24ab4bf07",
  "download_count": 22378,
  "thumbnail_url": "https://cdn.polyhaven.com/asset_img/thumbs/wine_barrel_01.png?width=256&height=256"
}