{
  "type": 1,
  "tags": [
    "gravel",
    "mud",
    "dirt",
    "rough",
    "pathway",
    "path",
    "road",
    "village"
  ],
  "date_published": 1529359200,
  "name": "Red Dirt Mud 01",
  "old_id": 103,
  "categories": [
    "terrain",
    "outdoor",
    "natural"
  ],
  "authors": {
    "Rob Tuytel": "All"
  },
  "dimensions": [
    1500,
    1500
  ],
  "max_resolution": [
    8192,
    8192
  ],
  "files_hash": "5b112074006dedd7ea5e2550f0d906cb20fb96e3",
  "download_count": 40132,
  "thumbnail_url": "https://cdn.polyhaven.com/asset_img/thumbs/red_dirt_mud_01.png?width=256&height=256"
}