{
  "date_published": 1665619200,
  "name": "Roots",
  "categories": [
    "outdoor",
    "natural",
    "floor"
  ],
  "type": 1,
  "reviewers": [
    "Rico Cilliers"
  ],
  "staging": null,
  "info": null,
  "tags": [
    "uneven",
    "old",
    "weathered",
    "brown",
    "dirty",
    "ground",
    "dry",
    "nature",
    "dirt",
    "tree",
    "forest"
  ],
  "authors": {
    "Dario Barresi": "Processing ",
    "Dimitrios Savva": "Photography"
  },
  "dimensions": [
    1670.0000762939453,
    1670.0000762939453
  ],
  "max_resolution": [
    8192,
    8192
  ],
  "files_hash": "dc49cea59048ed6511811d95505a37e17112fee1",
  "download_count": 6767,
  "thumbnail_url": "https://cdn.polyhaven.com/asset_img/thumbs/roots.png?width=256&height=256"
}