{
  "name": "Rubber Tiles",
  "categories": [
    "floor",
    "man made"
  ],
  "type": 1,
  "reviewers": [
    "Dario Barresi"
  ],
  "tags": [
    "tiles",
    "smooth",
    "rubber",
    "durable flooring",
    "waterproof tiles",
    "gym floor",
    "gym",
    "square"
  ],
  "authors": {
    "Amal Kumar": "All"
  },
  "info": null,
  "dimensions": [
    1999.9996423721313,
    1999.9996423721313
  ],
  "date_published": 1700524800,
  "staging": null,
  "max_resolution": [
    16384,
    16384
  ],
  "files_hash": "75066e1de003ab7a022e12497b54cf4c659cd2c1",
  "download_count": 82307,
  "thumbnail_url": "https://cdn.polyhaven.com/asset_img/thumbs/rubber_tiles.png?width=256&height=256"
}