{
  "evs_cap": 23,
  "type": 0,
  "tags": [
    "sun",
    "tree",
    "road",
    "asphalt",
    "parking",
    "park",
    "forest"
  ],
  "name": "Park Parking",
  "categories": [
    "outdoor",
    "nature",
    "midday",
    "natural light",
    "clear",
    "high contrast"
  ],
  "coords": [
    48.73027603099822,
    9.079748873908013
  ],
  "date_taken": 1630760040,
  "authors": {
    "Andreas Mischok": "All"
  },
  "date_published": 1636416000,
  "staging": null,
  "max_resolution": [
    19106,
    9553
  ],
  "files_hash": "240e564039dd7169144f167c5743001a7856c2ef",
  "download_count": 150707,
  "thumbnail_url": "https://cdn.polyhaven.com/asset_img/thumbs/park_parking.png?width=256&height=256"
}