{
  "evs_cap": 9,
  "type": 0,
  "tags": [
    "balcony",
    "waterfall",
    "mountain",
    "hill"
  ],
  "date_published": 1522879200,
  "name": "Sterkspruit Falls",
  "old_id": 253,
  "categories": [
    "outdoor",
    "nature",
    "sunrise-sunset",
    "partly cloudy",
    "low contrast",
    "natural light"
  ],
  "coords": [
    -29.04654,
    29.40439
  ],
  "date_taken": 1460559840,
  "authors": {
    "Greg Zaal": "All"
  },
  "files_hash": "12a4f4cf9b091c7d3305474c471efa452391a3f3",
  "max_resolution": [
    16384,
    8192
  ],
  "download_count": 14340,
  "thumbnail_url": "https://cdn.polyhaven.com/asset_img/thumbs/sterkspruit_falls.png?width=256&height=256"
}