{
  "type": 1,
  "name": "Moon 02",
  "authors": {
    "Greg Zaal": "Photography",
    "Rico Cilliers": "Photography",
    "Jenelle van Heerden": "Photography",
    "Dario Barresi": "Processing"
  },
  "reviewers": [
    "Jenelle van Heerden",
    "Rico Cilliers"
  ],
  "max_resolution": [
    16384,
    16384
  ],
  "dimensions": [
    3100.0001430511475,
    3100.0001430511475
  ],
  "info": "Captured at [PTS](https://www.pts.space/products/spacelab-rostock/)'s lunar test lab. [More info](https://blog.polyhaven.com/moon).",
  "staging": null,
  "tags": [
    "rough",
    "uneven",
    "dirt",
    "course",
    "exterior",
    "regolith",
    "lunar",
    "extraterrestrial",
    "space"
  ],
  "date_published": 1750336463,
  "categories": [
    "outdoor",
    "sand",
    "terrain",
    "collection: moon"
  ],
  "files_hash": "ba980c34cb3f5dc6a61de4be2a0a2cc6eb16debe",
  "download_count": 420,
  "thumbnail_url": "https://cdn.polyhaven.com/asset_img/thumbs/moon_02.png?width=256&height=256"
}